jupyterlab_webviz/__init__.py
jupyterlab_webviz/_version.py
jupyterlab_webviz/handlers.py
jupyterlab_webviz/labextension/package.json
jupyterlab_webviz/labextension/schemas/jupyterlab-webviz/package.json.orig
jupyterlab_webviz/labextension/schemas/jupyterlab-webviz/plugin.json
jupyterlab_webviz/labextension/static/534.d0aa78e0926636db529a.js
jupyterlab_webviz/labextension/static/993.d8a7efcfa557ee3ffa43.js
jupyterlab_webviz/labextension/static/remoteEntry.5342eaeb54b9c04968f1.js
jupyterlab_webviz/labextension/static/style.js
jupyterlab_webviz/webviz/app/favicon.ico
jupyterlab_webviz/webviz/app/index.html
jupyterlab_webviz/webviz/dist/1.js
jupyterlab_webviz/webviz/dist/1.js.LICENSE.txt
jupyterlab_webviz/webviz/dist/11.js
jupyterlab_webviz/webviz/dist/11.js.LICENSE.txt
jupyterlab_webviz/webviz/dist/114539537aa79c4ea55b3a60823d6716.bin
jupyterlab_webviz/webviz/dist/12.js
jupyterlab_webviz/webviz/dist/12.js.LICENSE.txt
jupyterlab_webviz/webviz/dist/13.js
jupyterlab_webviz/webviz/dist/13.js.LICENSE.txt
jupyterlab_webviz/webviz/dist/14.js
jupyterlab_webviz/webviz/dist/14.js.LICENSE.txt
jupyterlab_webviz/webviz/dist/15.js
jupyterlab_webviz/webviz/dist/15.js.LICENSE.txt
jupyterlab_webviz/webviz/dist/16.js
jupyterlab_webviz/webviz/dist/16.js.LICENSE.txt
jupyterlab_webviz/webviz/dist/17.js
jupyterlab_webviz/webviz/dist/17.js.LICENSE.txt
jupyterlab_webviz/webviz/dist/18.js
jupyterlab_webviz/webviz/dist/18.js.LICENSE.txt
jupyterlab_webviz/webviz/dist/19.js
jupyterlab_webviz/webviz/dist/19.js.LICENSE.txt
jupyterlab_webviz/webviz/dist/20.js
jupyterlab_webviz/webviz/dist/20.js.LICENSE.txt
jupyterlab_webviz/webviz/dist/21.js
jupyterlab_webviz/webviz/dist/21.js.LICENSE.txt
jupyterlab_webviz/webviz/dist/22.js
jupyterlab_webviz/webviz/dist/22.js.LICENSE.txt
jupyterlab_webviz/webviz/dist/23.js
jupyterlab_webviz/webviz/dist/23.js.LICENSE.txt
jupyterlab_webviz/webviz/dist/24.js
jupyterlab_webviz/webviz/dist/24.js.LICENSE.txt
jupyterlab_webviz/webviz/dist/25.js
jupyterlab_webviz-0.2.1.dist-info/LICENSE
jupyterlab_webviz-0.2.1.dist-info/METADATA
jupyterlab_webviz-0.2.1.dist-info/WHEEL
jupyterlab_webviz-0.2.1.dist-info/top_level.txt
jupyterlab_webviz-0.2.1.dist-info/RECORD
